{
  "project_info": {
    "project_number": "591276301249",
    "project_id": "b2023-gr2sw-jdmm-deber03",
    "storage_bucket": "b2023-gr2sw-jdmm-deber03.appspot.com"
  },
  "client": [
    {
      "client_info": {
        "mobilesdk_app_id": "1:591276301249:android:11e4dfec4c12ab3f53ed40",
        "android_client_info": {
          "package_name": "com.example.youtube"
        }
      },
      "oauth_client": [],
      "api_key": [
        {
          "current_key": "AIzaSyA38ziD_UA4kqLG_SdeCencanSxzF7juOQ"
        }
      ],
      "services": {
        "appinvite_service": {
          "other_platform_oauth_client": []
        }
      }
    }
  ],
  "configuration_version": "1"
}